defektor_api/__init__.py
defektor_api/api_client.py
defektor_api/configuration.py
defektor_api/exceptions.py
defektor_api/model_utils.py
defektor_api/rest.py
defektor_api/api/__init__.py
defektor_api/api/default_api.py
defektor_api/apis/__init__.py
defektor_api/model/__init__.py
defektor_api/model/campaign.py
defektor_api/model/data_collector.py
defektor_api/model/data_output_uri.py
defektor_api/model/docker_image.py
defektor_api/model/ijk.py
defektor_api/model/injektion.py
defektor_api/model/key_value.py
defektor_api/model/plan.py
defektor_api/model/run.py
defektor_api/model/slave.py
defektor_api/model/ssh_credentials.py
defektor_api/model/system_config.py
defektor_api/model/system_type.py
defektor_api/model/work_load.py
defektor_api/models/__init__.py
defektor_api-0.1.2.dist-info/METADATA
defektor_api-0.1.2.dist-info/WHEEL
defektor_api-0.1.2.dist-info/top_level.txt
defektor_api-0.1.2.dist-info/RECORD
