Metadata-Version: 2.1
Name: defektor-api
Version: 0.1.2
Summary: defektor OpenAPI Specification
Home-page: UNKNOWN
Author: OpenAPI Generator community
Author-email: sob@dei.uc.pt
License: UNKNOWN
Keywords: OpenAPI,OpenAPI-Generator,defektor OpenAPI Specification
Platform: UNKNOWN
Requires-Python: >=3.6
Requires-Dist: urllib3 (>=1.25.3)
Requires-Dist: python-dateutil
